fastslide/__init__.py
fastslide/_fastslide.so
fastslide-0.2.0.dist-info/WHEEL
fastslide-0.2.0.dist-info/METADATA
fastslide-0.2.0.dist-info/RECORD
