Metadata-Version: 2.1
Name: fastslide
Author: Jonas Teuwen
Author-email: j.teuwen@nki.nl
Home-page: https://github.com/NKI-AI/fastslide
License: Apache-2.0
Summary: High-performance, thread-safe digital pathology slide reader
Requires-Python: >=3.10
Version: 0.2.0
